MANIFEST.in
README.rst
setup.py
collective/__init__.py
collective/__init__.pyc
collective.js.d3.egg-info/PKG-INFO
collective.js.d3.egg-info/SOURCES.txt
collective.js.d3.egg-info/dependency_links.txt
collective.js.d3.egg-info/entry_points.txt
collective.js.d3.egg-info/namespace_packages.txt
collective.js.d3.egg-info/not-zip-safe
collective.js.d3.egg-info/requires.txt
collective.js.d3.egg-info/top_level.txt
collective/js/__init__.py
collective/js/__init__.pyc
collective/js/d3/__init__.py
collective/js/d3/configure.zcml
collective/js/d3/d3.min.js
collective/js/d3/tests.py
collective/js/d3/profiles/default/jsregistry.xml
collective/js/d3/profiles/default/metadata.xml
docs/HISTORY.txt
docs/LICENSE.GPL
docs/LICENSE.txt