Metadata-Version: 1.0
Name: collective.js.d3
Version: 3.0.8.1
Summary: D3.js integration for Plone
Home-page: https://github.com/collective/collective.js.d3
Author: Eric BREHAULT
Author-email: eric.brehault@makina-corpus.org
License: GPL
Keywords: Plone,d3.js
Platform: UNKNOWN
Classifier: Framework :: Plone
Classifier: Programming Language :: Python
